pylayers_project/__init__.py
pylayers_project/project.py
pylayers_project-0.3.dist-info/LICENSE
pylayers_project-0.3.dist-info/METADATA
pylayers_project-0.3.dist-info/WHEEL
pylayers_project-0.3.dist-info/top_level.txt
pylayers_project-0.3.dist-info/RECORD
